neolabci/__init__.py
neolabci/common.py
neolabci/index.py
neolabci/report_app.py
neolabci/version.py
neolabci/commands/__init__.py
neolabci/commands/check_config.py
neolabci/commands/init_template.py
neolabci/commands/run_all.py
neolabci/commands/run_finish.py
neolabci/commands/run_notify.py
neolabci/commands/run_report.py
neolabci/commands/run_test.py
neolabci/commands/run_upload.py
neolabci/commands/show_config.py
neolabci/commands/test_connect.py
neolabci/templates/android.yml
neolabci/templates/ios.yml
neolabci/templates/php.yml
neolabci/templates/ruby.yml
neolab_ci-0.2.1.dist-info/METADATA
neolab_ci-0.2.1.dist-info/WHEEL
neolab_ci-0.2.1.dist-info/entry_points.txt
neolab_ci-0.2.1.dist-info/top_level.txt
neolab_ci-0.2.1.dist-info/RECORD
